cargoloader/main.py
cargoloader-0.0.1.dist-info/LICENSE
cargoloader-0.0.1.dist-info/METADATA
cargoloader-0.0.1.dist-info/WHEEL
cargoloader-0.0.1.dist-info/entry_points.txt
cargoloader-0.0.1.dist-info/top_level.txt
cargoloader-0.0.1.dist-info/RECORD
